LICENSE
README
setup.py
mzStudio3/AdjustableProgress.py
mzStudio3/AreaWindow.py
mzStudio3/BlaisPepCalc.py
mzStudio3/BlaisPepCalcSlim_aui.py
mzStudio3/BlaisPepCalcSlim_aui2.py
mzStudio3/BlaisPepCalcSlim_aui3.py
mzStudio3/Comet_GUI.py
mzStudio3/DatabaseOperations.py
mzStudio3/FeatureImport.py
mzStudio3/FeaturePopUp.py
mzStudio3/FeaturePopUp_new.py
mzStudio3/Filter_management.py
mzStudio3/HTreeCtrl.py
mzStudio3/LabelCoverage.py
mzStudio3/ListBank.py
mzStudio3/MGrid.py
mzStudio3/MSO.py
mzStudio3/MascotSearch.py
mzStudio3/ModManager.py
mzStudio3/ObjectOrganizer.py
mzStudio3/Peptigram.py
mzStudio3/PopUpWins.py
mzStudio3/Progressgauge.py
mzStudio3/QueryBuilder.py
mzStudio3/RICviewLite.py
mzStudio3/RICviewLite_multi.py
mzStudio3/Settings.py
mzStudio3/SingleIDFrame.py
mzStudio3/SpecBase.py
mzStudio3/SpecBase_aui3.py
mzStudio3/SpecBase_new.py
mzStudio3/SpecObject.py
mzStudio3/SpecViewLite_build2.py
mzStudio3/Tandem_GUI.py
mzStudio3/Timing tests.py
mzStudio3/TreeCtrl.py
mzStudio3/TreeCtrl2.py
mzStudio3/TreeCtrlTest.py
mzStudio3/XICObject.py
mzStudio3/XICPalette.py
mzStudio3/additions.py
mzStudio3/autocomplete.py
mzStudio3/averagine.py
mzStudio3/check_search_type.py
mzStudio3/customProcessing.py
mzStudio3/dbFrame.py
mzStudio3/example_custom_function.py
mzStudio3/featureDetector_412.py
mzStudio3/featureDetector_412Averagine.py
mzStudio3/fit.py
mzStudio3/flatmenu_patched.py
mzStudio3/listctrl.py
mzStudio3/mgf.py
mzStudio3/miniCHNOPS.py
mzStudio3/mzAtomicYardstick.py
mzStudio3/mzAtomicYardstick_OLD.py
mzStudio3/mzBruker_wrapper.py
mzStudio3/mzGUI_standalone.py
mzStudio3/mzStudio3.py
mzStudio3/mzStudio_backup.py
mzStudio3/plot_patched.py
mzStudio3/spectral_process.py
mzStudio3/t2dv2.py
mzStudio3/textSpectrum.py
mzStudio3/timetest.py
mzStudio3/wiffTest.py
mzStudio3/workbench.py
mzStudio3/xls_extensions.py
mzStudio3.egg-info/PKG-INFO
mzStudio3.egg-info/SOURCES.txt
mzStudio3.egg-info/dependency_links.txt
mzStudio3.egg-info/requires.txt
mzStudio3.egg-info/top_level.txt