Metadata-Version: 2.1
Name: mzStudio3
Version: 2.1
Summary: Mass Spectrometry/Proteomics Data Analysis Application
Home-page: http://github.com/BlaisProteomics/mzStudio3
Author: Scott Ficarro, William Max Alexander
Author-email: Scott_Ficarro@dfci.harvard.edu
License: UNKNOWN
Platform: UNKNOWN
License-File: LICENSE
